<string_table>
    <string id="ui_mcm_ui_popup_messages_killfeed_title">
        <text>Killfeed</text>
    </string>
    <string id="ui_mcm_menu_apm_killfeed">
        <text>Killfeed</text>
    </string>

    <string id="ui_mcm_ui_popup_messages_apm_killfeed_options">
        <text>Опции</text>
    </string>
    <string id="ui_mcm_lst_apm_killfeed_all">
        <text>Все</text>
    </string>
    <string id="ui_mcm_lst_apm_killfeed_onlyPlayerKillsAndDeath">
        <text>Только убийства и смерть игрока</text>
    </string>
    <string id="ui_mcm_lst_apm_killfeed_onlyPlayerDeath">
        <text>Только смерть игрока</text>
    </string>


	<string id="st_apm_killfeed_killed_by_no_reason">
        <text>Зона поглотила вас</text>
    </string>
    <string id="st_apm_killfeed_suicide">
        <text>Вам наскучила жизнь</text>
    </string>
    <string id="st_apm_killfeed_killed_by">
        <text>Вас убили %s (%s)</text>
    </string>

    <string id="st_apm_killfeed_npc_killed_by_no_reason">
        <text>Зона поглотила %s (%s)</text>
    </string>
    <string id="st_apm_killfeed_npc_suicide">
        <text>%s (%s) надоела жизнь</text>
    </string>
    <string id="st_apm_killfeed_npc_killed_by_player">
        <text>Вы убили %s (%s)</text>
    </string>
    <string id="st_apm_killfeed_npc_killed_by">
        <text>%s (%s) был убит %s (%s)</text>
    </string>
</string_table>