<?xml version="1.0" encoding="windows-1251" ?>

<string_table>


<string id="st_drive_upgrade_name_a_pack">
<text>
"F1RMW4R3 1NST4LL3R" pendrive
</text>
</string>

<string id="st_drive_upgrade_desc_a_pack">
<text>
A pendrive containing various config files, scripts, and EXEs.
Able to instantly update the firmware of a device.
\nSeems too good to be true, but has been approved by top "scientists".\n \n
%c[ui_gray_3]PROPERTIES:\n
%c[d_blue] • %c[ui_gray_2] firmware updates\n
%c[d_blue] • %c[ui_gray_2] technological item\n
</text>
</string>


<string id="st_drive_upgrade_max_name_a_pack">
<text>
"4DV4NC3D F1RMW4R3 1NST4LL3R" pendrive
</text>
</string>

<string id="st_drive_upgrade_max_desc_a_pack">
<text>
A pendrive containing an excessive amount of advanced config files, scripts, and EXEs.
Able to instantly update the firmware of a device.
\nA direct upgrade to the previous version, and will not do anything without the preceding updates.\n \n
%c[ui_gray_3]PROPERTIES:\n
%c[d_blue] • %c[ui_gray_2] advanced firmware updates\n
%c[d_blue] • %c[ui_gray_2] technological item\n
</text>
</string>


<string id="st_drive_upgrade_oc_name_a_pack">
<text>
"0V3RCL0CK3R" pendrive
</text>
</string>

<string id="st_drive_upgrade_oc_desc_a_pack">
<text>
A pendrive containing specific software designed to push a device to it's absolute limits.
Will force the hardware to work at speeds and capabilities far beyond it's factory settings.
\nUpgrading your device with this drive will void the manufacturer's warranty!
Though, considering your current lifestyle, I doubt that matters.
\nRequires preceding firmware updates!\n \n
%c[ui_gray_3]PROPERTIES:\n
%c[d_blue] • %c[d_orange] overclocking software\n
%c[d_blue] • %c[ui_gray_2] technological item\n
</text>
</string>


<string id="st_drive_factory_reset_name_a_pack">
<text>
"MUND4N3" pendrive
</text>
</string>

<string id="st_drive_factory_reset_desc_a_pack">
<text>
A pendrive containing some basic config files, scripts, and EXEs.
Designed to reset a device back to it's factory settings.
\nHow dull...\n \n
%c[ui_gray_3]PROPERTIES:\n
%c[d_blue] • %c[0,250,250,0] factory reset\n
%c[d_blue] • %c[ui_gray_2] technological item\n
</text>
</string>


<string id="st_detector1_up_name_a_pack">
<text>
Echo detector Mk.2
</text>
</string>

<string id="st_detector1_up_desc_a_pack">
<text>
This dated anomalous activity detector produces an alarm signal when anomalous particles enter a special chamber as you approach an anomaly.
It can also register the presence of artefacts and measure the distance to the nearest one.
The distance is indicated by the frequency of the sound the detector emits.
To switch to artefact search mode, open the device's front cover.
\nHas been updated with new firmware to detect slightly more artefacts, slightly more effectively.\n \n
%c[ui_gray_3]PROPERTIES:\n
%c[d_blue] • %c[ui_gray_2] updated firmware\n
%c[d_blue] • %c[ui_gray_2] technological item\n
%c[d_blue] • %c[ui_gray_2] moderate electric power consumption\n
</text>
</string>


<string id="st_detector1_upmax_name_a_pack">
<text>
Echo detector Mk.3
</text>
</string>

<string id="st_detector1_upmax_desc_a_pack">
<text>
This dated anomalous activity detector produces an alarm signal when anomalous particles enter a special chamber as you approach an anomaly.
It can also register the presence of artefacts and measure the distance to the nearest one.
The distance is indicated by the frequency of the sound the detector emits.
To switch to artefact search mode, open the device's front cover.
\nHas been further updated with advanced firmware to detect every artefact known to science, and more effectively!\n \n
%c[ui_gray_3]PROPERTIES:\n
%c[d_blue] • %c[ui_gray_2] advanced firmware\n
%c[d_blue] • %c[ui_gray_2] technological item\n
%c[d_blue] • %c[ui_gray_2] high electric power consumption\n
</text>
</string>


<string id="st_detector1_upoc_name_a_pack">
<text>
"Reverberate" detector OC
</text>
</string>

<string id="st_detector1_upoc_desc_a_pack">
<text>
This dated anomalous activity detector produces an alarm signal when anomalous particles enter a special chamber as you approach an anomaly.
It can also register the presence of artefacts and measure the distance to the nearest one.
The distance is indicated by the frequency of the sound the detector emits.
To switch to artefact search mode, open the device's front cover.
\nIn addition to the previous updates, this device has now been overclocked. Will detect every artefact known to science far more effectively!\n \n
%c[ui_gray_3]PROPERTIES:\n
%c[d_blue] • %c[d_orange] overclocked\n
%c[d_blue] • %c[d_purple] VOIDED WARRANTY\n
%c[d_blue] • %c[ui_gray_2] technological item\n
%c[d_blue] • %c[ui_gray_2] very high electric power consumption\n
</text>
</string>


<string id="st_detector2_up_name_a_pack">
<text>
Bear detector Mk.2
</text>
</string>

<string id="st_detector2_up_desc_a_pack">
<text>
This last generation anomalous activity detector can be used to locate anomalous formations and has a colour diode panel, which not only indicates the direction of artefacts, but also measures the distance to them.
To switch to artefact search mode, open the device's front cover.
\nHas been updated with new firmware to detect every artefact known to science, slightly more effectively.\n \n
%c[ui_gray_3]PROPERTIES:\n
%c[d_blue] • %c[ui_gray_2] updated firmware\n
%c[d_blue] • %c[ui_gray_2] technological item\n
%c[d_blue] • %c[ui_gray_2] high electric power consumption\n
</text>
</string>


<string id="st_detector2_upmax_name_a_pack">
<text>
Bear detector Mk.3
</text>
</string>

<string id="st_detector2_upmax_desc_a_pack">
<text>
This last generation anomalous activity detector can be used to locate anomalous formations and has a colour diode panel, which not only indicates the direction of artefacts, but also measures the distance to them.
To switch to artefact search mode, open the device's front cover.
\nHas been further updated with advanced firmware to detect artefacts more effectively!\n \n
%c[ui_gray_3]PROPERTIES:\n
%c[d_blue] • %c[ui_gray_2] advanced firmware\n
%c[d_blue] • %c[ui_gray_2] technological item\n
%c[d_blue] • %c[ui_gray_2] high electric power consumption\n
</text>
</string>


<string id="st_detector2_upoc_name_a_pack">
<text>
"Yampil" detector OC
</text>
</string>

<string id="st_detector2_upoc_desc_a_pack">
<text>
This last generation anomalous activity detector can be used to locate anomalous formations and has a colour diode panel, which not only indicates the direction of artefacts, but also measures the distance to them.
To switch to artefact search mode, open the device's front cover.
\nIn addition to the previous updates, this device has now been overclocked. Will detect every artefact known to science far more effectively!\n \n
%c[ui_gray_3]PROPERTIES:\n
%c[d_blue] • %c[d_orange] overclocked\n
%c[d_blue] • %c[d_purple] VOIDED WARRANTY\n
%c[d_blue] • %c[ui_gray_2] technological item\n
%c[d_blue] • %c[ui_gray_2] very high electric power consumption\n
</text>
</string>


<string id="st_detector3_up_name_a_pack">
<text>
Veles detector Mk.2
</text>
</string>

<string id="st_detector3_up_desc_a_pack">
<text>
A next generation scientific detection scanner.
Thanks to three modernised detection chambers, the position of artefacts is shown on a special display screen.
When closed, the device registers only radiation and anomalies.
To switch to artefact search mode, open the front LED display.
When in search mode, the detector is capable of locating all artefacts known to science.
\nHas been updated with new firmware to detect artefacts slightly more effectively.\n \n
%c[ui_gray_3]PROPERTIES:\n
%c[d_blue] • %c[ui_gray_2] updated firmware\n
%c[d_blue] • %c[ui_gray_2] technological item\n
%c[d_blue] • %c[ui_gray_2] high electric power consumption\n
</text>
</string>


<string id="st_detector3_upmax_name_a_pack">
<text>
Veles detector Mk.3
</text>
</string>

<string id="st_detector3_upmax_desc_a_pack">
<text>
A next generation scientific detection scanner.
Thanks to three modernised detection chambers, the position of artefacts is shown on a special display screen.
When closed, the device registers only radiation and anomalies.
To switch to artefact search mode, open the front LED display.
When in search mode, the detector is capable of locating all artefacts known to science.
\nHas been further updated with advanced firmware to detect artefacts more effectively!\n \n
%c[ui_gray_3]PROPERTIES:\n
%c[d_blue] • %c[ui_gray_2] advanced firmware\n
%c[d_blue] • %c[ui_gray_2] technological item\n
%c[d_blue] • %c[ui_gray_2] very high electric power consumption\n
</text>
</string>


<string id="st_detector3_upoc_name_a_pack">
<text>
"Cattle God of the Underworld" detector OC
</text>
</string>

<string id="st_detector3_upoc_desc_a_pack">
<text>
A next generation scientific detection scanner.
Thanks to three modernised detection chambers, the position of artefacts is shown on a special display screen.
When closed, the device registers only radiation and anomalies.
To switch to artefact search mode, open the front LED display.
When in search mode, the detector is capable of locating all artefacts known to science.
\nIn addition to the previous updates, this device has now been overclocked. Will detect artefacts far more effectively!\n \n
%c[ui_gray_3]PROPERTIES:\n
%c[d_blue] • %c[d_orange] overclocked\n
%c[d_blue] • %c[d_purple] VOIDED WARRANTY\n
%c[d_blue] • %c[ui_gray_2] technological item\n
%c[d_blue] • %c[ui_gray_2] extreme electric power consumption\n
</text>
</string>


<string id="st_detector4_up_name_a_pack">
<text>
Svarog detector Mk.2
</text>
</string>

<string id="st_detector4_up_desc_a_pack">
<text>
A prototype of an expanded functionality anomalous frequency scanner.
This device comes with a program used to identify static areas of anomalous activity stored in its database, while retaining the ability to locate artefacts.
The position of anomalous areas and artefacts is displayed on a special screen.
The artefact search mode, which can be activated by opening the front LED display, has been modified to detect anomalous formations currently unknown to science.
\nHas been updated with new firmware to detect artefacts slightly more effectively.\n \n
%c[ui_gray_3]PROPERTIES:\n
%c[d_blue] • %c[ui_gray_2] updated firmware\n
%c[d_blue] • %c[ui_gray_2] technological item\n
%c[d_blue] • %c[ui_gray_2] high electric power consumption\n
</text>
</string>


<string id="st_detector4_upmax_name_a_pack">
<text>
Svarog detector Mk.3
</text>
</string>

<string id="st_detector4_upmax_desc_a_pack">
<text>
A prototype of an expanded functionality anomalous frequency scanner.
This device comes with a program used to identify static areas of anomalous activity stored in its database, while retaining the ability to locate artefacts.
The position of anomalous areas and artefacts is displayed on a special screen.
The artefact search mode, which can be activated by opening the front LED display, has been modified to detect anomalous formations currently unknown to science.
\nHas been further updated with advanced firmware to detect artefacts more effectively!\n \n
%c[ui_gray_3]PROPERTIES:\n
%c[d_blue] • %c[ui_gray_2] advanced firmware\n
%c[d_blue] • %c[ui_gray_2] technological item\n
%c[d_blue] • %c[ui_gray_2] very high electric power consumption\n
</text>
</string>


<string id="st_detector4_upoc_name_a_pack">
<text>
"Divine Blacksmith" detector OC
</text>
</string>

<string id="st_detector4_upoc_desc_a_pack">
<text>
A prototype of an expanded functionality anomalous frequency scanner.
This device comes with a program used to identify static areas of anomalous activity stored in its database, while retaining the ability to locate artefacts.
The position of anomalous areas and artefacts is displayed on a special screen.
The artefact search mode, which can be activated by opening the front LED display, has been modified to detect anomalous formations currently unknown to science.
\nIn addition to the previous updates, this device has now been overclocked. Will detect artefacts far more effectively!\n \n
%c[ui_gray_3]PROPERTIES:\n
%c[d_blue] • %c[d_orange] overclocked\n
%c[d_blue] • %c[d_purple] VOIDED WARRANTY\n
%c[d_blue] • %c[ui_gray_2] technological item\n
%c[d_blue] • %c[ui_gray_2] extreme electric power consumption\n
</text>
</string>


</string_table>